pysad/__init__.py
pysad/version.py
pysad/core/__init__.py
pysad/core/base_metric.py
pysad/core/base_model.py
pysad/core/base_postprocessor.py
pysad/core/base_statistic.py
pysad/core/base_streamer.py
pysad/core/base_transformer.py
pysad/evaluation/__init__.py
pysad/evaluation/metrics.py
pysad/evaluation/windowed_metric.py
pysad/models/__init__.py
pysad/models/exact_storm.py
pysad/models/half_space_trees.py
pysad/models/iforest_asd.py
pysad/models/inqmad.py
pysad/models/kitnet.py
pysad/models/knn_cad.py
pysad/models/loda.py
pysad/models/loop.py
pysad/models/median_absolute_deviation.py
pysad/models/null_model.py
pysad/models/perfect_model.py
pysad/models/random_model.py
pysad/models/relative_entropy.py
pysad/models/robust_random_cut_forest.py
pysad/models/rs_hash.py
pysad/models/standard_absolute_deviation.py
pysad/models/xstream.py
pysad/models/integrations/__init__.py
pysad/models/integrations/one_fit_model.py
pysad/models/integrations/pyod_model.py
pysad/models/integrations/reference_window_model.py
pysad/models/kitnet_model/KitNET.py
pysad/models/kitnet_model/__init__.py
pysad/models/kitnet_model/corClust.py
pysad/models/kitnet_model/dA.py
pysad/models/kitnet_model/utils.py
pysad/statistics/__init__.py
pysad/statistics/abs_statistic.py
pysad/statistics/average_meter.py
pysad/statistics/count_meter.py
pysad/statistics/max_meter.py
pysad/statistics/median_meter.py
pysad/statistics/min_meter.py
pysad/statistics/running_statistic.py
pysad/statistics/sum_meter.py
pysad/statistics/sum_squares_meter.py
pysad/statistics/variance_meter.py
pysad/transform/__init__.py
pysad/transform/ensemble/__init__.py
pysad/transform/ensemble/ensemblers.py
pysad/transform/postprocessing/__init__.py
pysad/transform/postprocessing/postprocessors.py
pysad/transform/postprocessing/running_postprocessors.py
pysad/transform/preprocessing/__init__.py
pysad/transform/preprocessing/identity_scaler.py
pysad/transform/preprocessing/instance_standard_scaler.py
pysad-0.3.4.dist-info/licenses/LICENSE
pysad-0.3.4.dist-info/METADATA
pysad-0.3.4.dist-info/WHEEL
pysad-0.3.4.dist-info/top_level.txt
pysad-0.3.4.dist-info/RECORD
