Metadata-Version: 2.4
Name: pysad
Version: 0.3.4
Summary: PySAD is an open-source python framework for anomaly detection on streaming multivariate data.
Home-page: https://github.com/selimfirat/pysad
Download-URL: https://github.com/selimfirat/pysad/archive/master.zip
Author: Selim Firat Yilmaz
Author-email: Selim Firat Yilmaz <yilmazselimfirat@gmail.com>
Maintainer-email: Selim Firat Yilmaz <yilmazselimfirat@gmail.com>
License: BSD 3-Clause License
Project-URL: Homepage, https://github.com/selimfirat/pysad
Project-URL: Documentation, https://pysad.readthedocs.io/
Project-URL: Repository, https://github.com/selimfirat/pysad.git
Project-URL: Bug Tracker, https://github.com/selimfirat/pysad/issues
Project-URL: Changelog, https://github.com/selimfirat/pysad/blob/master/CHANGES.txt
Keywords: outlier detection,anomaly detection,machine learning
Classifier: Development Status :: 2 - Pre-Alpha
Classifier: Intended Audience :: Education
Classifier: Intended Audience :: Financial and Insurance Industry
Classifier: Intended Audience :: Developers
Classifier: Intended Audience :: Science/Research
Classifier: Intended Audience :: Information Technology
Classifier: Topic :: Scientific/Engineering
Classifier: Topic :: Scientific/Engineering :: Artificial Intelligence
Classifier: Topic :: Software Development
Classifier: License :: OSI Approved :: BSD License
Classifier: Operating System :: Unix
Classifier: Operating System :: MacOS
Classifier: Operating System :: Microsoft :: Windows
Classifier: Programming Language :: Python :: 3.10
Classifier: Programming Language :: Python :: 3.11
Classifier: Programming Language :: Python :: 3.12
Classifier: Programming Language :: Python :: 3.13
Requires-Python: >=3.10
License-File: LICENSE
Requires-Dist: numpy
Requires-Dist: scikit-learn
Requires-Dist: scipy
Requires-Dist: pyod==2.0.5
Requires-Dist: combo==0.1.3
Provides-Extra: rrcf
Requires-Dist: rrcf==0.4.4; extra == "rrcf"
Provides-Extra: slop
Requires-Dist: PyNomaly==0.3.3; extra == "slop"
Provides-Extra: xstream
Requires-Dist: mmh3==2.5.1; extra == "xstream"
Provides-Extra: pandas
Requires-Dist: pandas; extra == "pandas"
Provides-Extra: inqmad
Requires-Dist: jax>=0.6.1; extra == "inqmad"
Requires-Dist: jaxlib>=0.6.1; extra == "inqmad"
Dynamic: author
Dynamic: download-url
Dynamic: home-page
Dynamic: license-file
Dynamic: requires-python
